firefly/__init__.py
firefly/app.py
firefly/client.py
firefly/main.py
firefly/utils.py
firefly/validator.py
firefly/version.py
firefly_python-0.1.15.dist-info/METADATA
firefly_python-0.1.15.dist-info/RECORD
firefly_python-0.1.15.dist-info/WHEEL
firefly_python-0.1.15.dist-info/entry_points.txt
firefly_python-0.1.15.dist-info/top_level.txt
tests/__init__.py
tests/test_app.py
tests/test_client.py
tests/test_main.py
tests/test_validator.py
