Metadata-Version: 1.0
Name: firefly-python
Version: 0.1.15
Summary: deploying functions made easy
Home-page: UNKNOWN
Author: rorodata
Author-email: rorodata.team@gmail.com
License: UNKNOWN
Platform: UNKNOWN
